Workbook

Sheet DashBoard
D1: Caixa: | E1: 20000 | G1: Até | H1: =IF(ReCarteira!M2="",TODAY(),ReCarteira!M2) -> 46036
B4: Carteira atual
B5: =DashBoardAux!C13 -> 27838.05
B7: Total aportado
B8: =DashBoardAux!C12 -> 26791.03
B10: Valorização
B11: =DashBoardAux!C14 -> 1047.02
B13: Valorização %
B14: =DashBoardAux!C15 -> 0.039080991

Sheet DashBoardAux
B2: Valores para caixa de combinaçao | E2: Matriz auxiliar: somatório por tipo de ativo | K2: Gráfico: composição do patrimônio | N2: Gráfico: maiores valores | R2: Maiores valores (tudo) | W2: Maiores valores (ações) | AB2: Maiores valores (FII)
B3: 1 | C3: Tudo | G3: 1 | H3: 2 | I3: 3 | K3: Ações | L3: =H6 -> 17506 | N3: Ordem | O3: Ativo | P3: Valor | R3: Ordem | S3: Ativo | T3: Valor | U3: Corresp | W3: Ordem | X3: Ativo | Y3: Valor | Z3: Corresp | AB3: Ordem | AC3: Ativo | AD3: Valor | AE3: Corresp
B4: 2 | C4: Ações | G4: Tudo | H4: Ações | I4: FII | K4: FII | L4: =I6 -> 10332.05 | N4: 10 | O4: =IF($C$8=1,S4,IF($C$8=2,X4,AC4)) -> - | P4: =IF($C$8=1,T4,IF($C$8=2,Y4,AD4)) -> 0 | R4: 10 | S4: =IF(ISNA(INDEX(TbCarteira[Ativo],U4,1)),"-",INDEX(TbCarteira[Ativo],U4,1)) -> - | T4: =IF(ISNUMBER(LARGE(TbCarteira[Total atual],R4)),LARGE(TbCarteira[Total atual],R4),0) -> 0 | U4: =MATCH(T4,TbCarteira[Total atual],0) -> #N/A | W4: 10 | X4: =IF(ISNA(INDEX(TbCarteiraAcoes[Ativo],Z4,1)),"-",INDEX(TbCarteiraAcoes[Ativo],Z4,1)) -> - | Y4: =IF(ISNUMBER(LARGE(TbCarteiraAcoes[Total atual],W4)),LARGE(TbCarteiraAcoes[Total atual],W4),0) -> 0 | Z4: =MATCH(Y4,TbCarteiraAcoes[Total atual],0) -> #N/A | AB4: 10 | AC4: =IF(ISNA(INDEX(TbCarteiraFII[Ativo],AE4,1)),"-",INDEX(TbCarteiraFII[Ativo],AE4,1)) -> - | AD4: =IF(ISNUMBER(LARGE(TbCarteiraFII[Total atual],AB4)),LARGE(TbCarteiraFII[Total atual],AB4),0) -> 0 | AE4: =MATCH(AD4,TbCarteiraFII[Total atual],0) -> #N/A
B5: 3 | C5: Fundos Imobiliários | E5: 1 | F5: Total aportado | G5: =SUM(TbCarteira[Total aportado]) -> 26791.03 | H5: =SUMIF(TbCarteira[Tipo],"EMPRESA",TbCarteira[Total aportado]) -> 17598 | I5: =SUMIF(TbCarteira[Tipo],"FII",TbCarteira[Total aportado]) -> 9193.03 | K5: Caixa | L5: =C9 -> 20000 | N5: 9 | O5: =IF($C$8=1,S5,IF($C$8=2,X5,AC5)) -> HGBS11 | P5: =IF($C$8=1,T5,IF($C$8=2,Y5,AD5)) -> 1754.82 | R5: 9 | S5: =IF(ISNA(INDEX(TbCarteira[Ativo],U5,1)),"-",INDEX(TbCarteira[Ativo],U5,1)) -> HGBS11 | T5: =IF(ISNUMBER(LARGE(TbCarteira[Total atual],R5)),LARGE(TbCarteira[Total atual],R5),0) -> 1754.82 | U5: =MATCH(T5,TbCarteira[Total atual],0) -> 5 | W5: 9 | X5: =IF(ISNA(INDEX(TbCarteiraAcoes[Ativo],Z5,1)),"-",INDEX(TbCarteiraAcoes[Ativo],Z5,1)) -> - | Y5: =IF(ISNUMBER(LARGE(TbCarteiraAcoes[Total atual],W5)),LARGE(TbCarteiraAcoes[Total atual],W5),0) -> 0 | Z5: =MATCH(Y5,TbCarteiraAcoes[Total atual],0) -> #N/A | AB5: 9 | AC5: =IF(ISNA(INDEX(TbCarteiraFII[Ativo],AE5,1)),"-",INDEX(TbCarteiraFII[Ativo],AE5,1)) -> - | AD5: =IF(ISNUMBER(LARGE(TbCarteiraFII[Total atual],AB5)),LARGE(TbCarteiraFII[Total atual],AB5),0) -> 0 | AE5: =MATCH(AD5,TbCarteiraFII[Total atual],0) -> #N/A
E6: 2 | F6: Carteira atual | G6: =SUM(TbCarteira[Total atual]) -> 27838.05 | H6: =SUMIF(TbCarteira[Tipo],"EMPRESA",TbCarteira[Total atual]) -> 17506 | I6: =SUMIF(TbCarteira[Tipo],"FII",TbCarteira[Total atual]) -> 10332.05 | N6: 8 | O6: =IF($C$8=1,S6,IF($C$8=2,X6,AC6)) -> TAEE4 | P6: =IF($C$8=1,T6,IF($C$8=2,Y6,AD6)) -> 1810 | R6: 8 | S6: =IF(ISNA(INDEX(TbCarteira[Ativo],U6,1)),"-",INDEX(TbCarteira[Ativo],U6,1)) -> TAEE4 | T6: =IF(ISNUMBER(LARGE(TbCarteira[Total atual],R6)),LARGE(TbCarteira[Total atual],R6),0) -> 1810 | U6: =MATCH(T6,TbCarteira[Total atual],0) -> 9 | W6: 8 | X6: =IF(ISNA(INDEX(TbCarteiraAcoes[Ativo],Z6,1)),"-",INDEX(TbCarteiraAcoes[Ativo],Z6,1)) -> - | Y6: =IF(ISNUMBER(LARGE(TbCarteiraAcoes[Total atual],W6)),LARGE(TbCarteiraAcoes[Total atual],W6),0) -> 0 | Z6: =MATCH(Y6,TbCarteiraAcoes[Total atual],0) -> #N/A | AB6: 8 | AC6: =IF(ISNA(INDEX(TbCarteiraFII[Ativo],AE6,1)),"-",INDEX(TbCarteiraFII[Ativo],AE6,1)) -> - | AD6: =IF(ISNUMBER(LARGE(TbCarteiraFII[Total atual],AB6)),LARGE(TbCarteiraFII[Total atual],AB6),0) -> 0 | AE6: =MATCH(AD6,TbCarteiraFII[Total atual],0) -> #N/A
B7: Entradas do usuário | E7: 3 | F7: Valorização | G7: =SUM(TbCarteira[Valorização]) -> 1047.02 | H7: =H6-H5 -> -92 | I7: =I6-I5 -> 1139.02 | N7: 7 | O7: =IF($C$8=1,S7,IF($C$8=2,X7,AC7)) -> CSNA3 | P7: =IF($C$8=1,T7,IF($C$8=2,Y7,AD7)) -> 2364 | R7: 7 | S7: =IF(ISNA(INDEX(TbCarteira[Ativo],U7,1)),"-",INDEX(TbCarteira[Ativo],U7,1)) -> CSNA3 | T7: =IF(ISNUMBER(LARGE(TbCarteira[Total atual],R7)),LARGE(TbCarteira[Total atual],R7),0) -> 2364 | U7: =MATCH(T7,TbCarteira[Total atual],0) -> 1 | W7: 7 | X7: =IF(ISNA(INDEX(TbCarteiraAcoes[Ativo],Z7,1)),"-",INDEX(TbCarteiraAcoes[Ativo],Z7,1)) -> - | Y7: =IF(ISNUMBER(LARGE(TbCarteiraAcoes[Total atual],W7)),LARGE(TbCarteiraAcoes[Total atual],W7),0) -> 0 | Z7: =MATCH(Y7,TbCarteiraAcoes[Total atual],0) -> #N/A | AB7: 7 | AC7: =IF(ISNA(INDEX(TbCarteiraFII[Ativo],AE7,1)),"-",INDEX(TbCarteiraFII[Ativo],AE7,1)) -> - | AD7: =IF(ISNUMBER(LARGE(TbCarteiraFII[Total atual],AB7)),LARGE(TbCarteiraFII[Total atual],AB7),0) -> 0 | AE7: =MATCH(AD7,TbCarteiraFII[Total atual],0) -> #N/A
B8: Caixa de combinação | C8: 1 | E8: 4 | F8: Valorização % | G8: =G6/G5-1 -> 0.039080991 | H8: =H6/H5-1 -> -0.0052278668 | I8: =I6/I5-1 -> 0.12390039 | N8: 6 | O8: =IF($C$8=1,S8,IF($C$8=2,X8,AC8)) -> ITSA4 | P8: =IF($C$8=1,T8,IF($C$8=2,Y8,AD8)) -> 2442 | R8: 6 | S8: =IF(ISNA(INDEX(TbCarteira[Ativo],U8,1)),"-",INDEX(TbCarteira[Ativo],U8,1)) -> ITSA4 | T8: =IF(ISNUMBER(LARGE(TbCarteira[Total atual],R8)),LARGE(TbCarteira[Total atual],R8),0) -> 2442 | U8: =MATCH(T8,TbCarteira[Total atual],0) -> 3 | W8: 6 | X8: =IF(ISNA(INDEX(TbCarteiraAcoes[Ativo],Z8,1)),"-",INDEX(TbCarteiraAcoes[Ativo],Z8,1)) -> - | Y8: =IF(ISNUMBER(LARGE(TbCarteiraAcoes[Total atual],W8)),LARGE(TbCarteiraAcoes[Total atual],W8),0) -> 0 | Z8: =MATCH(Y8,TbCarteiraAcoes[Total atual],0) -> #N/A | AB8: 6 | AC8: =IF(ISNA(INDEX(TbCarteiraFII[Ativo],AE8,1)),"-",INDEX(TbCarteiraFII[Ativo],AE8,1)) -> - | AD8: =IF(ISNUMBER(LARGE(TbCarteiraFII[Total atual],AB8)),LARGE(TbCarteiraFII[Total atual],AB8),0) -> 0 | AE8: =MATCH(AD8,TbCarteiraFII[Total atual],0) -> #N/A
B9: Valor em caixa | C9: =DashBoard!E1 -> 20000 | N9: 5 | O9: =IF($C$8=1,S9,IF($C$8=2,X9,AC9)) -> HGRE11 | P9: =IF($C$8=1,T9,IF($C$8=2,Y9,AD9)) -> 2696.86 | R9: 5 | S9: =IF(ISNA(INDEX(TbCarteira[Ativo],U9,1)),"-",INDEX(TbCarteira[Ativo],U9,1)) -> HGRE11 | T9: =IF(ISNUMBER(LARGE(TbCarteira[Total atual],R9)),LARGE(TbCarteira[Total atual],R9),0) -> 2696.86 | U9: =MATCH(T9,TbCarteira[Total atual],0) -> 7 | W9: 5 | X9: =IF(ISNA(INDEX(TbCarteiraAcoes[Ativo],Z9,1)),"-",INDEX(TbCarteiraAcoes[Ativo],Z9,1)) -> TAEE4 | Y9: =IF(ISNUMBER(LARGE(TbCarteiraAcoes[Total atual],W9)),LARGE(TbCarteiraAcoes[Total atual],W9),0) -> 1810 | Z9: =MATCH(Y9,TbCarteiraAcoes[Total atual],0) -> 5 | AB9: 5 | AC9: =IF(ISNA(INDEX(TbCarteiraFII[Ativo],AE9,1)),"-",INDEX(TbCarteiraFII[Ativo],AE9,1)) -> - | AD9: =IF(ISNUMBER(LARGE(TbCarteiraFII[Total atual],AB9)),LARGE(TbCarteiraFII[Total atual],AB9),0) -> 0 | AE9: =MATCH(AD9,TbCarteiraFII[Total atual],0) -> #N/A
N10: 4 | O10: =IF($C$8=1,S10,IF($C$8=2,X10,AC10)) -> KNRI11 | P10: =IF($C$8=1,T10,IF($C$8=2,Y10,AD10)) -> 2914.38 | R10: 4 | S10: =IF(ISNA(INDEX(TbCarteira[Ativo],U10,1)),"-",INDEX(TbCarteira[Ativo],U10,1)) -> KNRI11 | T10: =IF(ISNUMBER(LARGE(TbCarteira[Total atual],R10)),LARGE(TbCarteira[Total atual],R10),0) -> 2914.38 | U10: =MATCH(T10,TbCarteira[Total atual],0) -> 8 | W10: 4 | X10: =IF(ISNA(INDEX(TbCarteiraAcoes[Ativo],Z10,1)),"-",INDEX(TbCarteiraAcoes[Ativo],Z10,1)) -> CSNA3 | Y10: =IF(ISNUMBER(LARGE(TbCarteiraAcoes[Total atual],W10)),LARGE(TbCarteiraAcoes[Total atual],W10),0) -> 2364 | Z10: =MATCH(Y10,TbCarteiraAcoes[Total atual],0) -> 1 | AB10: 4 | AC10: =IF(ISNA(INDEX(TbCarteiraFII[Ativo],AE10,1)),"-",INDEX(TbCarteiraFII[Ativo],AE10,1)) -> HGBS11 | AD10: =IF(ISNUMBER(LARGE(TbCarteiraFII[Total atual],AB10)),LARGE(TbCarteiraFII[Total atual],AB10),0) -> 1754.82 | AE10: =MATCH(AD10,TbCarteiraFII[Total atual],0) -> 1
B11: Indicadores-chave de desempenho (KPI) | N11: 3 | O11: =IF($C$8=1,S11,IF($C$8=2,X11,AC11)) -> HGLG11 | P11: =IF($C$8=1,T11,IF($C$8=2,Y11,AD11)) -> 2965.99 | R11: 3 | S11: =IF(ISNA(INDEX(TbCarteira[Ativo],U11,1)),"-",INDEX(TbCarteira[Ativo],U11,1)) -> HGLG11 | T11: =IF(ISNUMBER(LARGE(TbCarteira[Total atual],R11)),LARGE(TbCarteira[Total atual],R11),0) -> 2965.99 | U11: =MATCH(T11,TbCarteira[Total atual],0) -> 6 | W11: 3 | X11: =IF(ISNA(INDEX(TbCarteiraAcoes[Ativo],Z11,1)),"-",INDEX(TbCarteiraAcoes[Ativo],Z11,1)) -> ITSA4 | Y11: =IF(ISNUMBER(LARGE(TbCarteiraAcoes[Total atual],W11)),LARGE(TbCarteiraAcoes[Total atual],W11),0) -> 2442 | Z11: =MATCH(Y11,TbCarteiraAcoes[Total atual],0) -> 3 | AB11: 3 | AC11: =IF(ISNA(INDEX(TbCarteiraFII[Ativo],AE11,1)),"-",INDEX(TbCarteiraFII[Ativo],AE11,1)) -> HGRE11 | AD11: =IF(ISNUMBER(LARGE(TbCarteiraFII[Total atual],AB11)),LARGE(TbCarteiraFII[Total atual],AB11),0) -> 2696.86 | AE11: =MATCH(AD11,TbCarteiraFII[Total atual],0) -> 3
B12: Total aportado | C12: =INDEX($G$5:$I$8,E5,$C$8) -> 26791.03 | N12: 2 | O12: =IF($C$8=1,S12,IF($C$8=2,X12,AC12)) -> FLRY3 | P12: =IF($C$8=1,T12,IF($C$8=2,Y12,AD12)) -> 4030 | R12: 2 | S12: =IF(ISNA(INDEX(TbCarteira[Ativo],U12,1)),"-",INDEX(TbCarteira[Ativo],U12,1)) -> FLRY3 | T12: =IF(ISNUMBER(LARGE(TbCarteira[Total atual],R12)),LARGE(TbCarteira[Total atual],R12),0) -> 4030 | U12: =MATCH(T12,TbCarteira[Total atual],0) -> 2 | W12: 2 | X12: =IF(ISNA(INDEX(TbCarteiraAcoes[Ativo],Z12,1)),"-",INDEX(TbCarteiraAcoes[Ativo],Z12,1)) -> FLRY3 | Y12: =IF(ISNUMBER(LARGE(TbCarteiraAcoes[Total atual],W12)),LARGE(TbCarteiraAcoes[Total atual],W12),0) -> 4030 | Z12: =MATCH(Y12,TbCarteiraAcoes[Total atual],0) -> 2 | AB12: 2 | AC12: =IF(ISNA(INDEX(TbCarteiraFII[Ativo],AE12,1)),"-",INDEX(TbCarteiraFII[Ativo],AE12,1)) -> KNRI11 | AD12: =IF(ISNUMBER(LARGE(TbCarteiraFII[Total atual],AB12)),LARGE(TbCarteiraFII[Total atual],AB12),0) -> 2914.38 | AE12: =MATCH(AD12,TbCarteiraFII[Total atual],0) -> 4
B13: Carteira atual | C13: =INDEX($G$5:$I$8,E6,$C$8) -> 27838.05 | N13: 1 | O13: =IF($C$8=1,S13,IF($C$8=2,X13,AC13)) -> PETR4 | P13: =IF($C$8=1,T13,IF($C$8=2,Y13,AD13)) -> 6860 | R13: 1 | S13: =IF(ISNA(INDEX(TbCarteira[Ativo],U13,1)),"-",INDEX(TbCarteira[Ativo],U13,1)) -> PETR4 | T13: =IF(ISNUMBER(LARGE(TbCarteira[Total atual],R13)),LARGE(TbCarteira[Total atual],R13),0) -> 6860 | U13: =MATCH(T13,TbCarteira[Total atual],0) -> 4 | W13: 1 | X13: =IF(ISNA(INDEX(TbCarteiraAcoes[Ativo],Z13,1)),"-",INDEX(TbCarteiraAcoes[Ativo],Z13,1)) -> PETR4 | Y13: =IF(ISNUMBER(LARGE(TbCarteiraAcoes[Total atual],W13)),LARGE(TbCarteiraAcoes[Total atual],W13),0) -> 6860 | Z13: =MATCH(Y13,TbCarteiraAcoes[Total atual],0) -> 4 | AB13: 1 | AC13: =IF(ISNA(INDEX(TbCarteiraFII[Ativo],AE13,1)),"-",INDEX(TbCarteiraFII[Ativo],AE13,1)) -> HGLG11 | AD13: =IF(ISNUMBER(LARGE(TbCarteiraFII[Total atual],AB13)),LARGE(TbCarteiraFII[Total atual],AB13),0) -> 2965.99 | AE13: =MATCH(AD13,TbCarteiraFII[Total atual],0) -> 2
B14: Valorização | C14: =INDEX($G$5:$I$8,E7,$C$8) -> 1047.02
B15: Valorização % | C15: =INDEX($G$5:$I$8,E8,$C$8) -> 0.039080991 | N15: Gráfico: maiores valorizações | R15: Maiores valorizações (tudo) | W15: Maiores valorizações (ações) | AB15: Maiores valorizações (FII)
N16: Ordem | O16: Ativo | P16: Valor | R16: Ordem | S16: Ativo | T16: Valorização % | U16: Corresp | W16: Ordem | X16: Ativo | Y16: Valorização % | Z16: Corresp | AB16: Ordem | AC16: Ativo | AD16: Valorização % | AE16: Corresp
N17: 10 | O17: =IF($C$8=1,S17,IF($C$8=2,X17,AC17)) -> - | P17: =IF($C$8=1,T17,IF($C$8=2,Y17,AD17)) -> 0 | R17: 10 | S17: =IF(ISNA(INDEX(TbCarteira[Ativo],U17,1)),"-",INDEX(TbCarteira[Ativo],U17,1)) -> - | T17: =IF(ISNUMBER(LARGE(TbCarteira[Valorização %],R17)),LARGE(TbCarteira[Valorização %],R17),0) -> 0 | U17: =MATCH(T17,TbCarteira[Valorização %],0) -> #N/A | W17: 10 | X17: =IF(ISNA(INDEX(TbCarteiraAcoes[Ativo],Z17,1)),"-",INDEX(TbCarteiraAcoes[Ativo],Z17,1)) -> - | Y17: =IF(ISNUMBER(LARGE(TbCarteiraAcoes[Valorização %],W17)),LARGE(TbCarteiraAcoes[Valorização %],W17),0) -> 0 | Z17: =MATCH(Y17,TbCarteiraAcoes[Valorização %],0) -> #N/A | AB17: 10 | AC17: =IF(ISNA(INDEX(TbCarteiraFII[Ativo],AE17,1)),"-",INDEX(TbCarteiraFII[Ativo],AE17,1)) -> - | AD17: =IF(ISNUMBER(LARGE(TbCarteiraFII[Valorização %],AB17)),LARGE(TbCarteiraFII[Valorização %],AB17),0) -> 0 | AE17: =MATCH(AD17,TbCarteiraFII[Valorização %],0) -> #N/A
N18: 9 | O18: =IF($C$8=1,S18,IF($C$8=2,X18,AC18)) -> CSNA3 | P18: =IF($C$8=1,T18,IF($C$8=2,Y18,AD18)) -> -0.15871886 | R18: 9 | S18: =IF(ISNA(INDEX(TbCarteira[Ativo],U18,1)),"-",INDEX(TbCarteira[Ativo],U18,1)) -> CSNA3 | T18: =IF(ISNUMBER(LARGE(TbCarteira[Valorização %],R18)),LARGE(TbCarteira[Valorização %],R18),0) -> -0.15871886 | U18: =MATCH(T18,TbCarteira[Valorização %],0) -> 1 | W18: 9 | X18: =IF(ISNA(INDEX(TbCarteiraAcoes[Ativo],Z18,1)),"-",INDEX(TbCarteiraAcoes[Ativo],Z18,1)) -> - | Y18: =IF(ISNUMBER(LARGE(TbCarteiraAcoes[Valorização %],W18)),LARGE(TbCarteiraAcoes[Valorização %],W18),0) -> 0 | Z18: =MATCH(Y18,TbCarteiraAcoes[Valorização %],0) -> #N/A | AB18: 9 | AC18: =IF(ISNA(INDEX(TbCarteiraFII[Ativo],AE18,1)),"-",INDEX(TbCarteiraFII[Ativo],AE18,1)) -> - | AD18: =IF(ISNUMBER(LARGE(TbCarteiraFII[Valorização %],AB18)),LARGE(TbCarteiraFII[Valorização %],AB18),0) -> 0 | AE18: =MATCH(AD18,TbCarteiraFII[Valorização %],0) -> #N/A
N19: 8 | O19: =IF($C$8=1,S19,IF($C$8=2,X19,AC19)) -> ITSA4 | P19: =IF($C$8=1,T19,IF($C$8=2,Y19,AD19)) -> -0.027866242 | R19: 8 | S19: =IF(ISNA(INDEX(TbCarteira[Ativo],U19,1)),"-",INDEX(TbCarteira[Ativo],U19,1)) -> ITSA4 | T19: =IF(ISNUMBER(LARGE(TbCarteira[Valorização %],R19)),LARGE(TbCarteira[Valorização %],R19),0) -> -0.027866242 | U19: =MATCH(T19,TbCarteira[Valorização %],0) -> 3 | W19: 8 | X19: =IF(ISNA(INDEX(TbCarteiraAcoes[Ativo],Z19,1)),"-",INDEX(TbCarteiraAcoes[Ativo],Z19,1)) -> - | Y19: =IF(ISNUMBER(LARGE(TbCarteiraAcoes[Valorização %],W19)),LARGE(TbCarteiraAcoes[Valorização %],W19),0) -> 0 | Z19: =MATCH(Y19,TbCarteiraAcoes[Valorização %],0) -> #N/A | AB19: 8 | AC19: =IF(ISNA(INDEX(TbCarteiraFII[Ativo],AE19,1)),"-",INDEX(TbCarteiraFII[Ativo],AE19,1)) -> - | AD19: =IF(ISNUMBER(LARGE(TbCarteiraFII[Valorização %],AB19)),LARGE(TbCarteiraFII[Valorização %],AB19),0) -> 0 | AE19: =MATCH(AD19,TbCarteiraFII[Valorização %],0) -> #N/A
N20: 7 | O20: =IF($C$8=1,S20,IF($C$8=2,X20,AC20)) -> FLRY3 | P20: =IF($C$8=1,T20,IF($C$8=2,Y20,AD20)) -> 0.00074497144 | R20: 7 | S20: =IF(ISNA(INDEX(TbCarteira[Ativo],U20,1)),"-",INDEX(TbCarteira[Ativo],U20,1)) -> FLRY3 | T20: =IF(ISNUMBER(LARGE(TbCarteira[Valorização %],R20)),LARGE(TbCarteira[Valorização %],R20),0) -> 0.00074497144 | U20: =MATCH(T20,TbCarteira[Valorização %],0) -> 2 | W20: 7 | X20: =IF(ISNA(INDEX(TbCarteiraAcoes[Ativo],Z20,1)),"-",INDEX(TbCarteiraAcoes[Ativo],Z20,1)) -> - | Y20: =IF(ISNUMBER(LARGE(TbCarteiraAcoes[Valorização %],W20)),LARGE(TbCarteiraAcoes[Valorização %],W20),0) -> 0 | Z20: =MATCH(Y20,TbCarteiraAcoes[Valorização %],0) -> #N/A | AB20: 7 | AC20: =IF(ISNA(INDEX(TbCarteiraFII[Ativo],AE20,1)),"-",INDEX(TbCarteiraFII[Ativo],AE20,1)) -> - | AD20: =IF(ISNUMBER(LARGE(TbCarteiraFII[Valorização %],AB20)),LARGE(TbCarteiraFII[Valorização %],AB20),0) -> 0 | AE20: =MATCH(AD20,TbCarteiraFII[Valorização %],0) -> #N/A
N21: 6 | O21: =IF($C$8=1,S21,IF($C$8=2,X21,AC21)) -> HGBS11 | P21: =IF($C$8=1,T21,IF($C$8=2,Y21,AD21)) -> 0.023606615 | R21: 6 | S21: =IF(ISNA(INDEX(TbCarteira[Ativo],U21,1)),"-",INDEX(TbCarteira[Ativo],U21,1)) -> HGBS11 | T21: =IF(ISNUMBER(LARGE(TbCarteira[Valorização %],R21)),LARGE(TbCarteira[Valorização %],R21),0) -> 0.023606615 | U21: =MATCH(T21,TbCarteira[Valorização %],0) -> 5 | W21: 6 | X21: =IF(ISNA(INDEX(TbCarteiraAcoes[Ativo],Z21,1)),"-",INDEX(TbCarteiraAcoes[Ativo],Z21,1)) -> - | Y21: =IF(ISNUMBER(LARGE(TbCarteiraAcoes[Valorização %],W21)),LARGE(TbCarteiraAcoes[Valorização %],W21),0) -> 0 | Z21: =MATCH(Y21,TbCarteiraAcoes[Valorização %],0) -> #N/A | AB21: 6 | AC21: =IF(ISNA(INDEX(TbCarteiraFII[Ativo],AE21,1)),"-",INDEX(TbCarteiraFII[Ativo],AE21,1)) -> - | AD21: =IF(ISNUMBER(LARGE(TbCarteiraFII[Valorização %],AB21)),LARGE(TbCarteiraFII[Valorização %],AB21),0) -> 0 | AE21: =MATCH(AD21,TbCarteiraFII[Valorização %],0) -> #N/A
N22: 5 | O22: =IF($C$8=1,S22,IF($C$8=2,X22,AC22)) -> PETR4 | P22: =IF($C$8=1,T22,IF($C$8=2,Y22,AD22)) -> 0.037193831 | R22: 5 | S22: =IF(ISNA(INDEX(TbCarteira[Ativo],U22,1)),"-",INDEX(TbCarteira[Ativo],U22,1)) -> PETR4 | T22: =IF(ISNUMBER(LARGE(TbCarteira[Valorização %],R22)),LARGE(TbCarteira[Valorização %],R22),0) -> 0.037193831 | U22: =MATCH(T22,TbCarteira[Valorização %],0) -> 4 | W22: 5 | X22: =IF(ISNA(INDEX(TbCarteiraAcoes[Ativo],Z22,1)),"-",INDEX(TbCarteiraAcoes[Ativo],Z22,1)) -> CSNA3 | Y22: =IF(ISNUMBER(LARGE(TbCarteiraAcoes[Valorização %],W22)),LARGE(TbCarteiraAcoes[Valorização %],W22),0) -> -0.15871886 | Z22: =MATCH(Y22,TbCarteiraAcoes[Valorização %],0) -> 1 | AB22: 5 | AC22: =IF(ISNA(INDEX(TbCarteiraFII[Ativo],AE22,1)),"-",INDEX(TbCarteiraFII[Ativo],AE22,1)) -> - | AD22: =IF(ISNUMBER(LARGE(TbCarteiraFII[Valorização %],AB22)),LARGE(TbCarteiraFII[Valorização %],AB22),0) -> 0 | AE22: =MATCH(AD22,TbCarteiraFII[Valorização %],0) -> #N/A
N23: 4 | O23: =IF($C$8=1,S23,IF($C$8=2,X23,AC23)) -> HGRE11 | P23: =IF($C$8=1,T23,IF($C$8=2,Y23,AD23)) -> 0.081959584 | R23: 4 | S23: =IF(ISNA(INDEX(TbCarteira[Ativo],U23,1)),"-",INDEX(TbCarteira[Ativo],U23,1)) -> HGRE11 | T23: =IF(ISNUMBER(LARGE(TbCarteira[Valorização %],R23)),LARGE(TbCarteira[Valorização %],R23),0) -> 0.081959584 | U23: =MATCH(T23,TbCarteira[Valorização %],0) -> 7 | W23: 4 | X23: =IF(ISNA(INDEX(TbCarteiraAcoes[Ativo],Z23,1)),"-",INDEX(TbCarteiraAcoes[Ativo],Z23,1)) -> ITSA4 | Y23: =IF(ISNUMBER(LARGE(TbCarteiraAcoes[Valorização %],W23)),LARGE(TbCarteiraAcoes[Valorização %],W23),0) -> -0.027866242 | Z23: =MATCH(Y23,TbCarteiraAcoes[Valorização %],0) -> 3 | AB23: 4 | AC23: =IF(ISNA(INDEX(TbCarteiraFII[Ativo],AE23,1)),"-",INDEX(TbCarteiraFII[Ativo],AE23,1)) -> HGBS11 | AD23: =IF(ISNUMBER(LARGE(TbCarteiraFII[Valorização %],AB23)),LARGE(TbCarteiraFII[Valorização %],AB23),0) -> 0.023606615 | AE23: =MATCH(AD23,TbCarteiraFII[Valorização %],0) -> 1
N24: 3 | O24: =IF($C$8=1,S24,IF($C$8=2,X24,AC24)) -> KNRI11 | P24: =IF($C$8=1,T24,IF($C$8=2,Y24,AD24)) -> 0.10590066 | R24: 3 | S24: =IF(ISNA(INDEX(TbCarteira[Ativo],U24,1)),"-",INDEX(TbCarteira[Ativo],U24,1)) -> KNRI11 | T24: =IF(ISNUMBER(LARGE(TbCarteira[Valorização %],R24)),LARGE(TbCarteira[Valorização %],R24),0) -> 0.10590066 | U24: =MATCH(T24,TbCarteira[Valorização %],0) -> 8 | W24: 3 | X24: =IF(ISNA(INDEX(TbCarteiraAcoes[Ativo],Z24,1)),"-",INDEX(TbCarteiraAcoes[Ativo],Z24,1)) -> FLRY3 | Y24: =IF(ISNUMBER(LARGE(TbCarteiraAcoes[Valorização %],W24)),LARGE(TbCarteiraAcoes[Valorização %],W24),0) -> 0.00074497144 | Z24: =MATCH(Y24,TbCarteiraAcoes[Valorização %],0) -> 2 | AB24: 3 | AC24: =IF(ISNA(INDEX(TbCarteiraFII[Ativo],AE24,1)),"-",INDEX(TbCarteiraFII[Ativo],AE24,1)) -> HGRE11 | AD24: =IF(ISNUMBER(LARGE(TbCarteiraFII[Valorização %],AB24)),LARGE(TbCarteiraFII[Valorização %],AB24),0) -> 0.081959584 | AE24: =MATCH(AD24,TbCarteiraFII[Valorização %],0) -> 3
N25: 2 | O25: =IF($C$8=1,S25,IF($C$8=2,X25,AC25)) -> TAEE4 | P25: =IF($C$8=1,T25,IF($C$8=2,Y25,AD25)) -> 0.10703364 | R25: 2 | S25: =IF(ISNA(INDEX(TbCarteira[Ativo],U25,1)),"-",INDEX(TbCarteira[Ativo],U25,1)) -> TAEE4 | T25: =IF(ISNUMBER(LARGE(TbCarteira[Valorização %],R25)),LARGE(TbCarteira[Valorização %],R25),0) -> 0.10703364 | U25: =MATCH(T25,TbCarteira[Valorização %],0) -> 9 | W25: 2 | X25: =IF(ISNA(INDEX(TbCarteiraAcoes[Ativo],Z25,1)),"-",INDEX(TbCarteiraAcoes[Ativo],Z25,1)) -> PETR4 | Y25: =IF(ISNUMBER(LARGE(TbCarteiraAcoes[Valorização %],W25)),LARGE(TbCarteiraAcoes[Valorização %],W25),0) -> 0.037193831 | Z25: =MATCH(Y25,TbCarteiraAcoes[Valorização %],0) -> 4 | AB25: 2 | AC25: =IF(ISNA(INDEX(TbCarteiraFII[Ativo],AE25,1)),"-",INDEX(TbCarteiraFII[Ativo],AE25,1)) -> KNRI11 | AD25: =IF(ISNUMBER(LARGE(TbCarteiraFII[Valorização %],AB25)),LARGE(TbCarteiraFII[Valorização %],AB25),0) -> 0.10590066 | AE25: =MATCH(AD25,TbCarteiraFII[Valorização %],0) -> 4
N26: 1 | O26: =IF($C$8=1,S26,IF($C$8=2,X26,AC26)) -> HGLG11 | P26: =IF($C$8=1,T26,IF($C$8=2,Y26,AD26)) -> 0.26168852 | R26: 1 | S26: =IF(ISNA(INDEX(TbCarteira[Ativo],U26,1)),"-",INDEX(TbCarteira[Ativo],U26,1)) -> HGLG11 | T26: =IF(ISNUMBER(LARGE(TbCarteira[Valorização %],R26)),LARGE(TbCarteira[Valorização %],R26),0) -> 0.26168852 | U26: =MATCH(T26,TbCarteira[Valorização %],0) -> 6 | W26: 1 | X26: =IF(ISNA(INDEX(TbCarteiraAcoes[Ativo],Z26,1)),"-",INDEX(TbCarteiraAcoes[Ativo],Z26,1)) -> TAEE4 | Y26: =IF(ISNUMBER(LARGE(TbCarteiraAcoes[Valorização %],W26)),LARGE(TbCarteiraAcoes[Valorização %],W26),0) -> 0.10703364 | Z26: =MATCH(Y26,TbCarteiraAcoes[Valorização %],0) -> 5 | AB26: 1 | AC26: =IF(ISNA(INDEX(TbCarteiraFII[Ativo],AE26,1)),"-",INDEX(TbCarteiraFII[Ativo],AE26,1)) -> HGLG11 | AD26: =IF(ISNUMBER(LARGE(TbCarteiraFII[Valorização %],AB26)),LARGE(TbCarteiraFII[Valorização %],AB26),0) -> 0.26168852 | AE26: =MATCH(AD26,TbCarteiraFII[Valorização %],0) -> 2

Sheet ReCarteira
B2: Ativo | C2: Tipo | D2: Cotação | E2: Total aportado | F2: Total qte | G2: PM | H2: Total atual | I2: Valorização | J2: Valorização % | L2: Até qual data?
B3: CSNA3 | C3: =VLOOKUP(TbCarteira[[#This Row],[Ativo]],TbAtivos!$C$3:$E$500,2,FALSE) -> EMPRESA | D3: =VLOOKUP(TbCarteira[[#This Row],[Ativo]],TbAtivos!$C$3:$E$500,3,FALSE) -> 7.88 | E3: =SUMIFS(TbAportes[Total],TbAportes[Ativo],TbCarteira[[#This Row],[Ativo]],TbAportes[Data],"<="&IF($M$2="",TODAY(),$M$2)) -> 2810 | F3: =SUMIFS(TbAportes[Qte],TbAportes[Ativo],TbCarteira[[#This Row],[Ativo]],TbAportes[Data],"<="&IF($M$2="",TODAY(),$M$2)) -> 300 | G3: =TbCarteira[[#This Row],[Total aportado]]/TbCarteira[[#This Row],[Total qte]] -> 9.3666667 | H3: =TbCarteira[[#This Row],[Total qte]]*TbCarteira[[#This Row],[Cotação]] -> 2364 | I3: =TbCarteira[[#This Row],[Total atual]]-TbCarteira[[#This Row],[Total aportado]] -> -446 | J3: =TbCarteira[[#This Row],[Total atual]]/TbCarteira[[#This Row],[Total aportado]]-1 -> -0.15871886
B4: FLRY3 | C4: =VLOOKUP(TbCarteira[[#This Row],[Ativo]],TbAtivos!$C$3:$E$500,2,FALSE) -> EMPRESA | D4: =VLOOKUP(TbCarteira[[#This Row],[Ativo]],TbAtivos!$C$3:$E$500,3,FALSE) -> 20.15 | E4: =SUMIFS(TbAportes[Total],TbAportes[Ativo],TbCarteira[[#This Row],[Ativo]],TbAportes[Data],"<="&IF($M$2="",TODAY(),$M$2)) -> 4027 | F4: =SUMIFS(TbAportes[Qte],TbAportes[Ativo],TbCarteira[[#This Row],[Ativo]],TbAportes[Data],"<="&IF($M$2="",TODAY(),$M$2)) -> 200 | G4: =TbCarteira[[#This Row],[Total aportado]]/TbCarteira[[#This Row],[Total qte]] -> 20.135 | H4: =TbCarteira[[#This Row],[Total qte]]*TbCarteira[[#This Row],[Cotação]] -> 4030 | I4: =TbCarteira[[#This Row],[Total atual]]-TbCarteira[[#This Row],[Total aportado]] -> 3 | J4: =TbCarteira[[#This Row],[Total atual]]/TbCarteira[[#This Row],[Total aportado]]-1 -> 0.00074497144
B5: ITSA4 | C5: =VLOOKUP(TbCarteira[[#This Row],[Ativo]],TbAtivos!$C$3:$E$500,2,FALSE) -> EMPRESA | D5: =VLOOKUP(TbCarteira[[#This Row],[Ativo]],TbAtivos!$C$3:$E$500,3,FALSE) -> 8.14 | E5: =SUMIFS(TbAportes[Total],TbAportes[Ativo],TbCarteira[[#This Row],[Ativo]],TbAportes[Data],"<="&IF($M$2="",TODAY(),$M$2)) -> 2512 | F5: =SUMIFS(TbAportes[Qte],TbAportes[Ativo],TbCarteira[[#This Row],[Ativo]],TbAportes[Data],"<="&IF($M$2="",TODAY(),$M$2)) -> 300 | G5: =TbCarteira[[#This Row],[Total aportado]]/TbCarteira[[#This Row],[Total qte]] -> 8.3733333 | H5: =TbCarteira[[#This Row],[Total qte]]*TbCarteira[[#This Row],[Cotação]] -> 2442 | I5: =TbCarteira[[#This Row],[Total atual]]-TbCarteira[[#This Row],[Total aportado]] -> -70 | J5: =TbCarteira[[#This Row],[Total atual]]/TbCarteira[[#This Row],[Total aportado]]-1 -> -0.027866242
B6: PETR4 | C6: =VLOOKUP(TbCarteira[[#This Row],[Ativo]],TbAtivos!$C$3:$E$500,2,FALSE) -> EMPRESA | D6: =VLOOKUP(TbCarteira[[#This Row],[Ativo]],TbAtivos!$C$3:$E$500,3,FALSE) -> 17.15 | E6: =SUMIFS(TbAportes[Total],TbAportes[Ativo],TbCarteira[[#This Row],[Ativo]],TbAportes[Data],"<="&IF($M$2="",TODAY(),$M$2)) -> 6614 | F6: =SUMIFS(TbAportes[Qte],TbAportes[Ativo],TbCarteira[[#This Row],[Ativo]],TbAportes[Data],"<="&IF($M$2="",TODAY(),$M$2)) -> 400 | G6: =TbCarteira[[#This Row],[Total aportado]]/TbCarteira[[#This Row],[Total qte]] -> 16.535 | H6: =TbCarteira[[#This Row],[Total qte]]*TbCarteira[[#This Row],[Cotação]] -> 6860 | I6: =TbCarteira[[#This Row],[Total atual]]-TbCarteira[[#This Row],[Total aportado]] -> 246 | J6: =TbCarteira[[#This Row],[Total atual]]/TbCarteira[[#This Row],[Total aportado]]-1 -> 0.037193831
B7: HGBS11 | C7: =VLOOKUP(TbCarteira[[#This Row],[Ativo]],TbAtivos!$C$3:$E$500,2,FALSE) -> FII | D7: =VLOOKUP(TbCarteira[[#This Row],[Ativo]],TbAtivos!$C$3:$E$500,3,FALSE) -> 194.98 | E7: =SUMIFS(TbAportes[Total],TbAportes[Ativo],TbCarteira[[#This Row],[Ativo]],TbAportes[Data],"<="&IF($M$2="",TODAY(),$M$2)) -> 1714.35 | F7: =SUMIFS(TbAportes[Qte],TbAportes[Ativo],TbCarteira[[#This Row],[Ativo]],TbAportes[Data],"<="&IF($M$2="",TODAY(),$M$2)) -> 9 | G7: =TbCarteira[[#This Row],[Total aportado]]/TbCarteira[[#This Row],[Total qte]] -> 190.48333 | H7: =TbCarteira[[#This Row],[Total qte]]*TbCarteira[[#This Row],[Cotação]] -> 1754.82 | I7: =TbCarteira[[#This Row],[Total atual]]-TbCarteira[[#This Row],[Total aportado]] -> 40.47 | J7: =TbCarteira[[#This Row],[Total atual]]/TbCarteira[[#This Row],[Total aportado]]-1 -> 0.023606615
B8: HGLG11 | C8: =VLOOKUP(TbCarteira[[#This Row],[Ativo]],TbAtivos!$C$3:$E$500,2,FALSE) -> FII | D8: =VLOOKUP(TbCarteira[[#This Row],[Ativo]],TbAtivos!$C$3:$E$500,3,FALSE) -> 174.47 | E8: =SUMIFS(TbAportes[Total],TbAportes[Ativo],TbCarteira[[#This Row],[Ativo]],TbAportes[Data],"<="&IF($M$2="",TODAY(),$M$2)) -> 2350.81 | F8: =SUMIFS(TbAportes[Qte],TbAportes[Ativo],TbCarteira[[#This Row],[Ativo]],TbAportes[Data],"<="&IF($M$2="",TODAY(),$M$2)) -> 17 | G8: =TbCarteira[[#This Row],[Total aportado]]/TbCarteira[[#This Row],[Total qte]] -> 138.28294 | H8: =TbCarteira[[#This Row],[Total qte]]*TbCarteira[[#This Row],[Cotação]] -> 2965.99 | I8: =TbCarteira[[#This Row],[Total atual]]-TbCarteira[[#This Row],[Total aportado]] -> 615.18 | J8: =TbCarteira[[#This Row],[Total atual]]/TbCarteira[[#This Row],[Total aportado]]-1 -> 0.26168852
B9: HGRE11 | C9: =VLOOKUP(TbCarteira[[#This Row],[Ativo]],TbAtivos!$C$3:$E$500,2,FALSE) -> FII | D9: =VLOOKUP(TbCarteira[[#This Row],[Ativo]],TbAtivos!$C$3:$E$500,3,FALSE) -> 141.94 | E9: =SUMIFS(TbAportes[Total],TbAportes[Ativo],TbCarteira[[#This Row],[Ativo]],TbAportes[Data],"<="&IF($M$2="",TODAY(),$M$2)) -> 2492.57 | F9: =SUMIFS(TbAportes[Qte],TbAportes[Ativo],TbCarteira[[#This Row],[Ativo]],TbAportes[Data],"<="&IF($M$2="",TODAY(),$M$2)) -> 19 | G9: =TbCarteira[[#This Row],[Total aportado]]/TbCarteira[[#This Row],[Total qte]] -> 131.18789 | H9: =TbCarteira[[#This Row],[Total qte]]*TbCarteira[[#This Row],[Cotação]] -> 2696.86 | I9: =TbCarteira[[#This Row],[Total atual]]-TbCarteira[[#This Row],[Total aportado]] -> 204.29 | J9: =TbCarteira[[#This Row],[Total atual]]/TbCarteira[[#This Row],[Total aportado]]-1 -> 0.081959584
B10: KNRI11 | C10: =VLOOKUP(TbCarteira[[#This Row],[Ativo]],TbAtivos!$C$3:$E$500,2,FALSE) -> FII | D10: =VLOOKUP(TbCarteira[[#This Row],[Ativo]],TbAtivos!$C$3:$E$500,3,FALSE) -> 161.91 | E10: =SUMIFS(TbAportes[Total],TbAportes[Ativo],TbCarteira[[#This Row],[Ativo]],TbAportes[Data],"<="&IF($M$2="",TODAY(),$M$2)) -> 2635.3 | F10: =SUMIFS(TbAportes[Qte],TbAportes[Ativo],TbCarteira[[#This Row],[Ativo]],TbAportes[Data],"<="&IF($M$2="",TODAY(),$M$2)) -> 18 | G10: =TbCarteira[[#This Row],[Total aportado]]/TbCarteira[[#This Row],[Total qte]] -> 146.40556 | H10: =TbCarteira[[#This Row],[Total qte]]*TbCarteira[[#This Row],[Cotação]] -> 2914.38 | I10: =TbCarteira[[#This Row],[Total atual]]-TbCarteira[[#This Row],[Total aportado]] -> 279.08 | J10: =TbCarteira[[#This Row],[Total atual]]/TbCarteira[[#This Row],[Total aportado]]-1 -> 0.10590066
B11: TAEE4 | C11: =VLOOKUP(TbCarteira[[#This Row],[Ativo]],TbAtivos!$C$3:$E$500,2,FALSE) -> EMPRESA | D11: =VLOOKUP(TbCarteira[[#This Row],[Ativo]],TbAtivos!$C$3:$E$500,3,FALSE) -> 9.05 | E11: =SUMIFS(TbAportes[Total],TbAportes[Ativo],TbCarteira[[#This Row],[Ativo]],TbAportes[Data],"<="&IF($M$2="",TODAY(),$M$2)) -> 1635 | F11: =SUMIFS(TbAportes[Qte],TbAportes[Ativo],TbCarteira[[#This Row],[Ativo]],TbAportes[Data],"<="&IF($M$2="",TODAY(),$M$2)) -> 200 | G11: =TbCarteira[[#This Row],[Total aportado]]/TbCarteira[[#This Row],[Total qte]] -> 8.175 | H11: =TbCarteira[[#This Row],[Total qte]]*TbCarteira[[#This Row],[Cotação]] -> 1810 | I11: =TbCarteira[[#This Row],[Total atual]]-TbCarteira[[#This Row],[Total aportado]] -> 175 | J11: =TbCarteira[[#This Row],[Total atual]]/TbCarteira[[#This Row],[Total aportado]]-1 -> 0.10703364
B12: Total | E12: =SUBTOTAL(109,TbCarteira[Total aportado]) -> 26791.03 | H12: =SUBTOTAL(109,TbCarteira[Total atual]) -> 27838.05 | I12: =SUBTOTAL(109,TbCarteira[Valorização]) -> 1047.02

Sheet ReCarteiraAções
B2: Ativo | C2: Tipo | D2: Cotação | E2: Total aportado | F2: Total qte | G2: PM | H2: Total atual | I2: Valorização | J2: Valorização % | L2: Até qual data?
B3: CSNA3 | C3: =VLOOKUP(TbCarteiraAcoes[[#This Row],[Ativo]],TbAtivos!$C$3:$E$500,2,FALSE) -> EMPRESA | D3: =VLOOKUP(TbCarteiraAcoes[[#This Row],[Ativo]],TbAtivos!$C$3:$E$500,3,FALSE) -> 7.88 | E3: =SUMIFS(TbAportes[Total],TbAportes[Ativo],TbCarteiraAcoes[[#This Row],[Ativo]],TbAportes[Data],"<="&IF($M$2="",TODAY(),$M$2)) -> 2810 | F3: =SUMIFS(TbAportes[Qte],TbAportes[Ativo],TbCarteiraAcoes[[#This Row],[Ativo]],TbAportes[Data],"<="&IF($M$2="",TODAY(),$M$2)) -> 300 | G3: =TbCarteiraAcoes[[#This Row],[Total aportado]]/TbCarteiraAcoes[[#This Row],[Total qte]] -> 9.3666667 | H3: =TbCarteiraAcoes[[#This Row],[Total qte]]*TbCarteiraAcoes[[#This Row],[Cotação]] -> 2364 | I3: =TbCarteiraAcoes[[#This Row],[Total atual]]-TbCarteiraAcoes[[#This Row],[Total aportado]] -> -446 | J3: =TbCarteiraAcoes[[#This Row],[Total atual]]/TbCarteiraAcoes[[#This Row],[Total aportado]]-1 -> -0.15871886
B4: FLRY3 | C4: =VLOOKUP(TbCarteiraAcoes[[#This Row],[Ativo]],TbAtivos!$C$3:$E$500,2,FALSE) -> EMPRESA | D4: =VLOOKUP(TbCarteiraAcoes[[#This Row],[Ativo]],TbAtivos!$C$3:$E$500,3,FALSE) -> 20.15 | E4: =SUMIFS(TbAportes[Total],TbAportes[Ativo],TbCarteiraAcoes[[#This Row],[Ativo]],TbAportes[Data],"<="&IF($M$2="",TODAY(),$M$2)) -> 4027 | F4: =SUMIFS(TbAportes[Qte],TbAportes[Ativo],TbCarteiraAcoes[[#This Row],[Ativo]],TbAportes[Data],"<="&IF($M$2="",TODAY(),$M$2)) -> 200 | G4: =TbCarteiraAcoes[[#This Row],[Total aportado]]/TbCarteiraAcoes[[#This Row],[Total qte]] -> 20.135 | H4: =TbCarteiraAcoes[[#This Row],[Total qte]]*TbCarteiraAcoes[[#This Row],[Cotação]] -> 4030 | I4: =TbCarteiraAcoes[[#This Row],[Total atual]]-TbCarteiraAcoes[[#This Row],[Total aportado]] -> 3 | J4: =TbCarteiraAcoes[[#This Row],[Total atual]]/TbCarteiraAcoes[[#This Row],[Total aportado]]-1 -> 0.00074497144
B5: ITSA4 | C5: =VLOOKUP(TbCarteiraAcoes[[#This Row],[Ativo]],TbAtivos!$C$3:$E$500,2,FALSE) -> EMPRESA | D5: =VLOOKUP(TbCarteiraAcoes[[#This Row],[Ativo]],TbAtivos!$C$3:$E$500,3,FALSE) -> 8.14 | E5: =SUMIFS(TbAportes[Total],TbAportes[Ativo],TbCarteiraAcoes[[#This Row],[Ativo]],TbAportes[Data],"<="&IF($M$2="",TODAY(),$M$2)) -> 2512 | F5: =SUMIFS(TbAportes[Qte],TbAportes[Ativo],TbCarteiraAcoes[[#This Row],[Ativo]],TbAportes[Data],"<="&IF($M$2="",TODAY(),$M$2)) -> 300 | G5: =TbCarteiraAcoes[[#This Row],[Total aportado]]/TbCarteiraAcoes[[#This Row],[Total qte]] -> 8.3733333 | H5: =TbCarteiraAcoes[[#This Row],[Total qte]]*TbCarteiraAcoes[[#This Row],[Cotação]] -> 2442 | I5: =TbCarteiraAcoes[[#This Row],[Total atual]]-TbCarteiraAcoes[[#This Row],[Total aportado]] -> -70 | J5: =TbCarteiraAcoes[[#This Row],[Total atual]]/TbCarteiraAcoes[[#This Row],[Total aportado]]-1 -> -0.027866242
B6: PETR4 | C6: =VLOOKUP(TbCarteiraAcoes[[#This Row],[Ativo]],TbAtivos!$C$3:$E$500,2,FALSE) -> EMPRESA | D6: =VLOOKUP(TbCarteiraAcoes[[#This Row],[Ativo]],TbAtivos!$C$3:$E$500,3,FALSE) -> 17.15 | E6: =SUMIFS(TbAportes[Total],TbAportes[Ativo],TbCarteiraAcoes[[#This Row],[Ativo]],TbAportes[Data],"<="&IF($M$2="",TODAY(),$M$2)) -> 6614 | F6: =SUMIFS(TbAportes[Qte],TbAportes[Ativo],TbCarteiraAcoes[[#This Row],[Ativo]],TbAportes[Data],"<="&IF($M$2="",TODAY(),$M$2)) -> 400 | G6: =TbCarteiraAcoes[[#This Row],[Total aportado]]/TbCarteiraAcoes[[#This Row],[Total qte]] -> 16.535 | H6: =TbCarteiraAcoes[[#This Row],[Total qte]]*TbCarteiraAcoes[[#This Row],[Cotação]] -> 6860 | I6: =TbCarteiraAcoes[[#This Row],[Total atual]]-TbCarteiraAcoes[[#This Row],[Total aportado]] -> 246 | J6: =TbCarteiraAcoes[[#This Row],[Total atual]]/TbCarteiraAcoes[[#This Row],[Total aportado]]-1 -> 0.037193831
B7: TAEE4 | C7: =VLOOKUP(TbCarteiraAcoes[[#This Row],[Ativo]],TbAtivos!$C$3:$E$500,2,FALSE) -> EMPRESA | D7: =VLOOKUP(TbCarteiraAcoes[[#This Row],[Ativo]],TbAtivos!$C$3:$E$500,3,FALSE) -> 9.05 | E7: =SUMIFS(TbAportes[Total],TbAportes[Ativo],TbCarteiraAcoes[[#This Row],[Ativo]],TbAportes[Data],"<="&IF($M$2="",TODAY(),$M$2)) -> 1635 | F7: =SUMIFS(TbAportes[Qte],TbAportes[Ativo],TbCarteiraAcoes[[#This Row],[Ativo]],TbAportes[Data],"<="&IF($M$2="",TODAY(),$M$2)) -> 200 | G7: =TbCarteiraAcoes[[#This Row],[Total aportado]]/TbCarteiraAcoes[[#This Row],[Total qte]] -> 8.175 | H7: =TbCarteiraAcoes[[#This Row],[Total qte]]*TbCarteiraAcoes[[#This Row],[Cotação]] -> 1810 | I7: =TbCarteiraAcoes[[#This Row],[Total atual]]-TbCarteiraAcoes[[#This Row],[Total aportado]] -> 175 | J7: =TbCarteiraAcoes[[#This Row],[Total atual]]/TbCarteiraAcoes[[#This Row],[Total aportado]]-1 -> 0.10703364
B8: Total | E8: =SUBTOTAL(109,TbCarteiraAcoes[Total aportado]) -> 17598 | H8: =SUBTOTAL(109,TbCarteiraAcoes[Total atual]) -> 17506 | I8: =SUBTOTAL(109,TbCarteiraAcoes[Valorização]) -> -92

Sheet ReCarteiraFII
B2: Ativo | C2: Tipo | D2: Cotação | E2: Total aportado | F2: Total qte | G2: PM | H2: Total atual | I2: Valorização | J2: Valorização % | L2: Até qual data?
B3: HGBS11 | C3: =VLOOKUP(TbCarteiraFII[[#This Row],[Ativo]],TbAtivos!$C$3:$E$500,2,FALSE) -> FII | D3: =VLOOKUP(TbCarteiraFII[[#This Row],[Ativo]],TbAtivos!$C$3:$E$500,3,FALSE) -> 194.98 | E3: =SUMIFS(TbAportes[Total],TbAportes[Ativo],TbCarteiraFII[[#This Row],[Ativo]],TbAportes[Data],"<="&IF($M$2="",TODAY(),$M$2)) -> 1714.35 | F3: =SUMIFS(TbAportes[Qte],TbAportes[Ativo],TbCarteiraFII[[#This Row],[Ativo]],TbAportes[Data],"<="&IF($M$2="",TODAY(),$M$2)) -> 9 | G3: =TbCarteiraFII[[#This Row],[Total aportado]]/TbCarteiraFII[[#This Row],[Total qte]] -> 190.48333 | H3: =TbCarteiraFII[[#This Row],[Total qte]]*TbCarteiraFII[[#This Row],[Cotação]] -> 1754.82 | I3: =TbCarteiraFII[[#This Row],[Total atual]]-TbCarteiraFII[[#This Row],[Total aportado]] -> 40.47 | J3: =TbCarteiraFII[[#This Row],[Total atual]]/TbCarteiraFII[[#This Row],[Total aportado]]-1 -> 0.023606615
B4: HGLG11 | C4: =VLOOKUP(TbCarteiraFII[[#This Row],[Ativo]],TbAtivos!$C$3:$E$500,2,FALSE) -> FII | D4: =VLOOKUP(TbCarteiraFII[[#This Row],[Ativo]],TbAtivos!$C$3:$E$500,3,FALSE) -> 174.47 | E4: =SUMIFS(TbAportes[Total],TbAportes[Ativo],TbCarteiraFII[[#This Row],[Ativo]],TbAportes[Data],"<="&IF($M$2="",TODAY(),$M$2)) -> 2350.81 | F4: =SUMIFS(TbAportes[Qte],TbAportes[Ativo],TbCarteiraFII[[#This Row],[Ativo]],TbAportes[Data],"<="&IF($M$2="",TODAY(),$M$2)) -> 17 | G4: =TbCarteiraFII[[#This Row],[Total aportado]]/TbCarteiraFII[[#This Row],[Total qte]] -> 138.28294 | H4: =TbCarteiraFII[[#This Row],[Total qte]]*TbCarteiraFII[[#This Row],[Cotação]] -> 2965.99 | I4: =TbCarteiraFII[[#This Row],[Total atual]]-TbCarteiraFII[[#This Row],[Total aportado]] -> 615.18 | J4: =TbCarteiraFII[[#This Row],[Total atual]]/TbCarteiraFII[[#This Row],[Total aportado]]-1 -> 0.26168852
B5: HGRE11 | C5: =VLOOKUP(TbCarteiraFII[[#This Row],[Ativo]],TbAtivos!$C$3:$E$500,2,FALSE) -> FII | D5: =VLOOKUP(TbCarteiraFII[[#This Row],[Ativo]],TbAtivos!$C$3:$E$500,3,FALSE) -> 141.94 | E5: =SUMIFS(TbAportes[Total],TbAportes[Ativo],TbCarteiraFII[[#This Row],[Ativo]],TbAportes[Data],"<="&IF($M$2="",TODAY(),$M$2)) -> 2492.57 | F5: =SUMIFS(TbAportes[Qte],TbAportes[Ativo],TbCarteiraFII[[#This Row],[Ativo]],TbAportes[Data],"<="&IF($M$2="",TODAY(),$M$2)) -> 19 | G5: =TbCarteiraFII[[#This Row],[Total aportado]]/TbCarteiraFII[[#This Row],[Total qte]] -> 131.18789 | H5: =TbCarteiraFII[[#This Row],[Total qte]]*TbCarteiraFII[[#This Row],[Cotação]] -> 2696.86 | I5: =TbCarteiraFII[[#This Row],[Total atual]]-TbCarteiraFII[[#This Row],[Total aportado]] -> 204.29 | J5: =TbCarteiraFII[[#This Row],[Total atual]]/TbCarteiraFII[[#This Row],[Total aportado]]-1 -> 0.081959584
B6: KNRI11 | C6: =VLOOKUP(TbCarteiraFII[[#This Row],[Ativo]],TbAtivos!$C$3:$E$500,2,FALSE) -> FII | D6: =VLOOKUP(TbCarteiraFII[[#This Row],[Ativo]],TbAtivos!$C$3:$E$500,3,FALSE) -> 161.91 | E6: =SUMIFS(TbAportes[Total],TbAportes[Ativo],TbCarteiraFII[[#This Row],[Ativo]],TbAportes[Data],"<="&IF($M$2="",TODAY(),$M$2)) -> 2635.3 | F6: =SUMIFS(TbAportes[Qte],TbAportes[Ativo],TbCarteiraFII[[#This Row],[Ativo]],TbAportes[Data],"<="&IF($M$2="",TODAY(),$M$2)) -> 18 | G6: =TbCarteiraFII[[#This Row],[Total aportado]]/TbCarteiraFII[[#This Row],[Total qte]] -> 146.40556 | H6: =TbCarteiraFII[[#This Row],[Total qte]]*TbCarteiraFII[[#This Row],[Cotação]] -> 2914.38 | I6: =TbCarteiraFII[[#This Row],[Total atual]]-TbCarteiraFII[[#This Row],[Total aportado]] -> 279.08 | J6: =TbCarteiraFII[[#This Row],[Total atual]]/TbCarteiraFII[[#This Row],[Total aportado]]-1 -> 0.10590066
B7: Total | E7: =SUBTOTAL(109,TbCarteiraFII[Total aportado]) -> 9193.03 | H7: =SUBTOTAL(109,TbCarteiraFII[Total atual]) -> 10332.05 | I7: =SUBTOTAL(109,TbCarteiraFII[Valorização]) -> 1139.02

Sheet ReProventos
B3: Soma de Valor Líquido | C3: Rótulos de Coluna
B4: Rótulos de Linha | C4: 2018/12 | D4: 2019/01 | E4: 2019/02 | F4: 2019/03 | G4: 2019/04 | H4: 2019/05 | I4: 2019/06 | J4: 2019/07 | K4: 2019/08 | L4: 2019/09 | M4: 2019/10 | N4: 2020/01 | O4: Total Geral
B5: EMPRESA | C5: 39.48 | D5: 61 | E5: 65.43 | F5: 163.66 | G5: 162.75 | H5: 156.14 | I5: 166 | J5: 162.75 | K5: 156.14 | L5: 166 | M5: 484.89 | N5: 162.75 | O5: 1946.99
B6: CSNA3 | L6: 166 | O6: 166
B7: FLRY3 | F7: 163.66 | K7: 156.14 | O7: 319.8
B8: ITSA4 | C8: 39.48 | E8: 65.43 | G8: 162.75 | I8: 166 | M8: 328.75 | O8: 762.41
B9: PETR4 | D9: 61 | J9: 162.75 | O9: 223.75
B10: TAEE4 | H10: 156.14 | M10: 156.14 | N10: 162.75 | O10: 475.03
B11: FII | C11: 217.66 | D11: 228.62 | E11: 358.32 | F11: 308.72 | G11: 433.18 | H11: 358.32 | I11: 308.72 | J11: 433.18 | K11: 357.29 | L11: 308.72 | M11: 1100.22 | N11: 433.18 | O11: 4846.13
B12: HGBS11 | C12: 63 | D12: 75.71 | E12: 61 | F12: 37.44 | G12: 61 | H12: 61 | I12: 37.44 | J12: 61 | K12: 59.97 | L12: 37.44 | M12: 159.44 | N12: 61 | O12: 775.44
B13: HGLG11 | C13: 81 | D13: 39.36 | E13: 99 | F13: 52.02 | G13: 180.6 | H13: 99 | I13: 52.02 | J13: 180.6 | K13: 99 | L13: 52.02 | M13: 331.62 | N13: 180.6 | O13: 1446.84
B14: HGRE11 | C14: 38.89 | D14: 51.8 | E14: 99.9 | F14: 42.14 | G14: 38.4 | H14: 99.9 | I14: 42.14 | J14: 38.4 | K14: 99.9 | L14: 42.14 | M14: 180.44 | N14: 38.4 | O14: 812.45
B15: KNRI11 | C15: 34.77 | D15: 61.75 | E15: 98.42 | F15: 177.12 | G15: 153.18 | H15: 98.42 | I15: 177.12 | J15: 153.18 | K15: 98.42 | L15: 177.12 | M15: 428.72 | N15: 153.18 | O15: 1811.4
B16: Total Geral | C16: 257.14 | D16: 289.62 | E16: 423.75 | F16: 472.38 | G16: 595.93 | H16: 514.46 | I16: 474.72 | J16: 595.93 | K16: 513.43 | L16: 474.72 | M16: 1585.11 | N16: 595.93 | O16: 6793.12

Sheet ReAportes
B3: Soma de Total | C3: Rótulos de Coluna
B4: Rótulos de Linha | C4: 2018/12 | D4: 2019/01 | E4: 2019/02 | F4: 2019/03 | G4: 2019/04 | H4: 2019/05 | I4: 2019/06 | J4: 2019/07 | K4: 2019/08 | L4: 2019/09 | M4: 2019/10 | N4: 2019/11 | O4: 2019/12 | P4: 2020/01 | Q4: Total Geral
B5: EMPRESA | C5: 1594 | D5: 1644 | E5: 788 | F5: 1985 | H5: 1721 | I5: 1591 | J5: 2042 | K5: 1766 | L5: 1022 | M5: 1613 | N5: 963 | O5: 869 | Q5: 17598
B6: CSNA3 | C6: 833 | H6: 955 | L6: 1022 | Q6: 2810
B7: FLRY3 | F7: 1985 | J7: 2042 | Q7: 4027
B8: ITSA4 | C8: 761 | E8: 788 | N8: 963 | Q8: 2512
B9: PETR4 | D9: 1644 | I9: 1591 | K9: 1766 | M9: 1613 | Q9: 6614
B10: TAEE4 | H10: 766 | O10: 869 | Q10: 1635
B11: FII | D11: 704.9 | E11: 991.52 | F11: 551.46 | G11: 635.83 | I11: 679.05 | J11: 191.74 | K11: 972.58 | L11: 268.2 | M11: 971.15 | N11: 430.65 | O11: 716.15 | P11: 2079.8 | Q11: 9193.03
B12: HGBS11 | F12: 551.46 | J12: 191.74 | M12: 971.15 | Q12: 1714.35
B13: HGLG11 | D13: 704.9 | G13: 242.68 | K13: 972.58 | N13: 430.65 | Q13: 2350.81
B14: HGRE11 | E14: 991.52 | I14: 679.05 | L14: 268.2 | P14: 553.8 | Q14: 2492.57
B15: KNRI11 | G15: 393.15 | O15: 716.15 | P15: 1526 | Q15: 2635.3
B16: Total Geral | C16: 1594 | D16: 2348.9 | E16: 1779.52 | F16: 2536.46 | G16: 635.83 | H16: 1721 | I16: 2270.05 | J16: 2233.74 | K16: 2738.58 | L16: 1290.2 | M16: 2584.15 | N16: 1393.65 | O16: 1585.15 | P16: 2079.8 | Q16: 26791.03

Sheet TbAportes
B2: Data | C2: Ativo | D2: Qte | E2: Valor unitário | F2: Custo | G2: Total | H2: Tipo | I2: Ano | J2: Mês | K2: Ano/Mês
B3: 43444 | C3: ITSA4 | D3: 100 | E3: 7.51 | F3: 10 | G3: =TbAportes[[#This Row],[Valor unitário]]*TbAportes[[#This Row],[Qte]]+TbAportes[[#This Row],[Custo]] -> 761 | H3: =VLOOKUP(TbAportes[[#This Row],[Ativo]],TbAtivos!$C$3:$E$500,2,FALSE) -> EMPRESA | I3: =YEAR(TbAportes[[#This Row],[Data]]) -> 2018 | J3: =MONTH(TbAportes[[#This Row],[Data]]) -> 12 | K3: =CONCATENATE(TbAportes[[#This Row],[Ano]],"/",IF(TbAportes[[#This Row],[Mês]]<10,"0",""),TbAportes[[#This Row],[Mês]]) -> 2018/12
B4: 43444 | C4: CSNA3 | D4: 100 | E4: 8.23 | F4: 10 | G4: =TbAportes[[#This Row],[Valor unitário]]*TbAportes[[#This Row],[Qte]]+TbAportes[[#This Row],[Custo]] -> 833 | H4: =VLOOKUP(TbAportes[[#This Row],[Ativo]],TbAtivos!$C$3:$E$500,2,FALSE) -> EMPRESA | I4: =YEAR(TbAportes[[#This Row],[Data]]) -> 2018 | J4: =MONTH(TbAportes[[#This Row],[Data]]) -> 12 | K4: =CONCATENATE(TbAportes[[#This Row],[Ano]],"/",IF(TbAportes[[#This Row],[Mês]]<10,"0",""),TbAportes[[#This Row],[Mês]]) -> 2018/12
B5: 43475 | C5: PETR4 | D5: 100 | E5: 16.34 | F5: 10 | G5: =TbAportes[[#This Row],[Valor unitário]]*TbAportes[[#This Row],[Qte]]+TbAportes[[#This Row],[Custo]] -> 1644 | H5: =VLOOKUP(TbAportes[[#This Row],[Ativo]],TbAtivos!$C$3:$E$500,2,FALSE) -> EMPRESA | I5: =YEAR(TbAportes[[#This Row],[Data]]) -> 2019 | J5: =MONTH(TbAportes[[#This Row],[Data]]) -> 1 | K5: =CONCATENATE(TbAportes[[#This Row],[Ano]],"/",IF(TbAportes[[#This Row],[Mês]]<10,"0",""),TbAportes[[#This Row],[Mês]]) -> 2019/01
B6: 43475 | C6: HGLG11 | D6: 5 | E6: 140.98 | F6: 0 | G6: =TbAportes[[#This Row],[Valor unitário]]*TbAportes[[#This Row],[Qte]]+TbAportes[[#This Row],[Custo]] -> 704.9 | H6: =VLOOKUP(TbAportes[[#This Row],[Ativo]],TbAtivos!$C$3:$E$500,2,FALSE) -> FII | I6: =YEAR(TbAportes[[#This Row],[Data]]) -> 2019 | J6: =MONTH(TbAportes[[#This Row],[Data]]) -> 1 | K6: =CONCATENATE(TbAportes[[#This Row],[Ano]],"/",IF(TbAportes[[#This Row],[Mês]]<10,"0",""),TbAportes[[#This Row],[Mês]]) -> 2019/01
B7: 43506 | C7: ITSA4 | D7: 100 | E7: 7.78 | F7: 10 | G7: =TbAportes[[#This Row],[Valor unitário]]*TbAportes[[#This Row],[Qte]]+TbAportes[[#This Row],[Custo]] -> 788 | H7: =VLOOKUP(TbAportes[[#This Row],[Ativo]],TbAtivos!$C$3:$E$500,2,FALSE) -> EMPRESA | I7: =YEAR(TbAportes[[#This Row],[Data]]) -> 2019 | J7: =MONTH(TbAportes[[#This Row],[Data]]) -> 2 | K7: =CONCATENATE(TbAportes[[#This Row],[Ano]],"/",IF(TbAportes[[#This Row],[Mês]]<10,"0",""),TbAportes[[#This Row],[Mês]]) -> 2019/02
B8: 43506 | C8: HGRE11 | D8: 8 | E8: 123.94 | F8: 0 | G8: =TbAportes[[#This Row],[Valor unitário]]*TbAportes[[#This Row],[Qte]]+TbAportes[[#This Row],[Custo]] -> 991.52 | H8: =VLOOKUP(TbAportes[[#This Row],[Ativo]],TbAtivos!$C$3:$E$500,2,FALSE) -> FII | I8: =YEAR(TbAportes[[#This Row],[Data]]) -> 2019 | J8: =MONTH(TbAportes[[#This Row],[Data]]) -> 2 | K8: =CONCATENATE(TbAportes[[#This Row],[Ano]],"/",IF(TbAportes[[#This Row],[Mês]]<10,"0",""),TbAportes[[#This Row],[Mês]]) -> 2019/02
B9: 43534 | C9: FLRY3 | D9: 100 | E9: 19.75 | F9: 10 | G9: =TbAportes[[#This Row],[Valor unitário]]*TbAportes[[#This Row],[Qte]]+TbAportes[[#This Row],[Custo]] -> 1985 | H9: =VLOOKUP(TbAportes[[#This Row],[Ativo]],TbAtivos!$C$3:$E$500,2,FALSE) -> EMPRESA | I9: =YEAR(TbAportes[[#This Row],[Data]]) -> 2019 | J9: =MONTH(TbAportes[[#This Row],[Data]]) -> 3 | K9: =CONCATENATE(TbAportes[[#This Row],[Ano]],"/",IF(TbAportes[[#This Row],[Mês]]<10,"0",""),TbAportes[[#This Row],[Mês]]) -> 2019/03
B10: 43534 | C10: HGBS11 | D10: 3 | E10: 183.82 | F10: 0 | G10: =TbAportes[[#This Row],[Valor unitário]]*TbAportes[[#This Row],[Qte]]+TbAportes[[#This Row],[Custo]] -> 551.46 | H10: =VLOOKUP(TbAportes[[#This Row],[Ativo]],TbAtivos!$C$3:$E$500,2,FALSE) -> FII | I10: =YEAR(TbAportes[[#This Row],[Data]]) -> 2019 | J10: =MONTH(TbAportes[[#This Row],[Data]]) -> 3 | K10: =CONCATENATE(TbAportes[[#This Row],[Ano]],"/",IF(TbAportes[[#This Row],[Mês]]<10,"0",""),TbAportes[[#This Row],[Mês]]) -> 2019/03
B11: 43565 | C11: HGLG11 | D11: 2 | E11: 121.34 | F11: 0 | G11: =TbAportes[[#This Row],[Valor unitário]]*TbAportes[[#This Row],[Qte]]+TbAportes[[#This Row],[Custo]] -> 242.68 | H11: =VLOOKUP(TbAportes[[#This Row],[Ativo]],TbAtivos!$C$3:$E$500,2,FALSE) -> FII | I11: =YEAR(TbAportes[[#This Row],[Data]]) -> 2019 | J11: =MONTH(TbAportes[[#This Row],[Data]]) -> 4 | K11: =CONCATENATE(TbAportes[[#This Row],[Ano]],"/",IF(TbAportes[[#This Row],[Mês]]<10,"0",""),TbAportes[[#This Row],[Mês]]) -> 2019/04
B12: 43565 | C12: KNRI11 | D12: 3 | E12: 131.05 | F12: 0 | G12: =TbAportes[[#This Row],[Valor unitário]]*TbAportes[[#This Row],[Qte]]+TbAportes[[#This Row],[Custo]] -> 393.15 | H12: =VLOOKUP(TbAportes[[#This Row],[Ativo]],TbAtivos!$C$3:$E$500,2,FALSE) -> FII | I12: =YEAR(TbAportes[[#This Row],[Data]]) -> 2019 | J12: =MONTH(TbAportes[[#This Row],[Data]]) -> 4 | K12: =CONCATENATE(TbAportes[[#This Row],[Ano]],"/",IF(TbAportes[[#This Row],[Mês]]<10,"0",""),TbAportes[[#This Row],[Mês]]) -> 2019/04
B13: 43595 | C13: CSNA3 | D13: 100 | E13: 9.45 | F13: 10 | G13: =TbAportes[[#This Row],[Valor unitário]]*TbAportes[[#This Row],[Qte]]+TbAportes[[#This Row],[Custo]] -> 955 | H13: =VLOOKUP(TbAportes[[#This Row],[Ativo]],TbAtivos!$C$3:$E$500,2,FALSE) -> EMPRESA | I13: =YEAR(TbAportes[[#This Row],[Data]]) -> 2019 | J13: =MONTH(TbAportes[[#This Row],[Data]]) -> 5 | K13: =CONCATENATE(TbAportes[[#This Row],[Ano]],"/",IF(TbAportes[[#This Row],[Mês]]<10,"0",""),TbAportes[[#This Row],[Mês]]) -> 2019/05
B14: 43595 | C14: TAEE4 | D14: 100 | E14: 7.56 | F14: 10 | G14: =TbAportes[[#This Row],[Valor unitário]]*TbAportes[[#This Row],[Qte]]+TbAportes[[#This Row],[Custo]] -> 766 | H14: =VLOOKUP(TbAportes[[#This Row],[Ativo]],TbAtivos!$C$3:$E$500,2,FALSE) -> EMPRESA | I14: =YEAR(TbAportes[[#This Row],[Data]]) -> 2019 | J14: =MONTH(TbAportes[[#This Row],[Data]]) -> 5 | K14: =CONCATENATE(TbAportes[[#This Row],[Ano]],"/",IF(TbAportes[[#This Row],[Mês]]<10,"0",""),TbAportes[[#This Row],[Mês]]) -> 2019/05
... B30: 43840 | C30: HGRE11 | D30: 4 | E30: 138.45 | F30: 0 | G30: =TbAportes[[#This Row],[Valor unitário]]*TbAportes[[#This Row],[Qte]]+TbAportes[[#This Row],[Custo]] -> 553.8 | H30: =VLOOKUP(TbAportes[[#This Row],[Ativo]],TbAtivos!$C$3:$E$500,2,FALSE) -> FII | I30: =YEAR(TbAportes[[#This Row],[Data]]) -> 2020 | J30: =MONTH(TbAportes[[#This Row],[Data]]) -> 1 | K30: =CONCATENATE(TbAportes[[#This Row],[Ano]],"/",IF(TbAportes[[#This Row],[Mês]]<10,"0",""),TbAportes[[#This Row],[Mês]]) -> 2020/01

Sheet TbProventos
B2: Cod | C2: Ativo | D2: Qte | E2: Valor Bruto | F2: IR | G2: Valor Líquido | H2: Data | I2: Ano/Mês | J2: Tipo
B3: 13 | C3: ITSA4 | D3: 100 | E3: 39.48 | F3: 0 | G3: 39.48 | H3: 43449 | I3: =CONCATENATE(YEAR(TbProventos[[#This Row],[Data]]),"/",IF(MONTH(TbProventos[[#This Row],[Data]])<10,"0",""),MONTH(TbProventos[[#This Row],[Data]])) -> 2018/12 | J3: =VLOOKUP(TbProventos[[#This Row],[Ativo]],TbAtivos!$C$3:$E$500,2,FALSE) -> EMPRESA
B4: 14 | C4: HGBS11 | D4: 100 | E4: 63 | F4: 0 | G4: 63 | H4: 43451 | I4: =CONCATENATE(YEAR(TbProventos[[#This Row],[Data]]),"/",IF(MONTH(TbProventos[[#This Row],[Data]])<10,"0",""),MONTH(TbProventos[[#This Row],[Data]])) -> 2018/12 | J4: =VLOOKUP(TbProventos[[#This Row],[Ativo]],TbAtivos!$C$3:$E$500,2,FALSE) -> FII
B5: 14 | C5: HGLG11 | D5: 100 | E5: 81 | F5: 0 | G5: 81 | H5: 43451 | I5: =CONCATENATE(YEAR(TbProventos[[#This Row],[Data]]),"/",IF(MONTH(TbProventos[[#This Row],[Data]])<10,"0",""),MONTH(TbProventos[[#This Row],[Data]])) -> 2018/12 | J5: =VLOOKUP(TbProventos[[#This Row],[Ativo]],TbAtivos!$C$3:$E$500,2,FALSE) -> FII
B6: 14 | C6: HGRE11 | D6: 100 | E6: 38.89 | F6: 0 | G6: 38.89 | H6: 43451 | I6: =CONCATENATE(YEAR(TbProventos[[#This Row],[Data]]),"/",IF(MONTH(TbProventos[[#This Row],[Data]])<10,"0",""),MONTH(TbProventos[[#This Row],[Data]])) -> 2018/12 | J6: =VLOOKUP(TbProventos[[#This Row],[Ativo]],TbAtivos!$C$3:$E$500,2,FALSE) -> FII
B7: 14 | C7: KNRI11 | D7: 100 | E7: 34.77 | F7: 0 | G7: 34.77 | H7: 43451 | I7: =CONCATENATE(YEAR(TbProventos[[#This Row],[Data]]),"/",IF(MONTH(TbProventos[[#This Row],[Data]])<10,"0",""),MONTH(TbProventos[[#This Row],[Data]])) -> 2018/12 | J7: =VLOOKUP(TbProventos[[#This Row],[Ativo]],TbAtivos!$C$3:$E$500,2,FALSE) -> FII
B8: 13 | C8: PETR4 | D8: 100 | E8: 67 | F8: 6 | G8: 61 | H8: 43480 | I8: =CONCATENATE(YEAR(TbProventos[[#This Row],[Data]]),"/",IF(MONTH(TbProventos[[#This Row],[Data]])<10,"0",""),MONTH(TbProventos[[#This Row],[Data]])) -> 2019/01 | J8: =VLOOKUP(TbProventos[[#This Row],[Ativo]],TbAtivos!$C$3:$E$500,2,FALSE) -> EMPRESA
B9: 14 | C9: HGBS11 | D9: 100 | E9: 75.71 | F9: 0 | G9: 75.71 | H9: 43482 | I9: =CONCATENATE(YEAR(TbProventos[[#This Row],[Data]]),"/",IF(MONTH(TbProventos[[#This Row],[Data]])<10,"0",""),MONTH(TbProventos[[#This Row],[Data]])) -> 2019/01 | J9: =VLOOKUP(TbProventos[[#This Row],[Ativo]],TbAtivos!$C$3:$E$500,2,FALSE) -> FII
B10: 14 | C10: HGLG11 | D10: 100 | E10: 39.36 | F10: 0 | G10: 39.36 | H10: 43482 | I10: =CONCATENATE(YEAR(TbProventos[[#This Row],[Data]]),"/",IF(MONTH(TbProventos[[#This Row],[Data]])<10,"0",""),MONTH(TbProventos[[#This Row],[Data]])) -> 2019/01 | J10: =VLOOKUP(TbProventos[[#This Row],[Ativo]],TbAtivos!$C$3:$E$500,2,FALSE) -> FII
B11: 14 | C11: HGRE11 | D11: 100 | E11: 51.8 | F11: 0 | G11: 51.8 | H11: 43482 | I11: =CONCATENATE(YEAR(TbProventos[[#This Row],[Data]]),"/",IF(MONTH(TbProventos[[#This Row],[Data]])<10,"0",""),MONTH(TbProventos[[#This Row],[Data]])) -> 2019/01 | J11: =VLOOKUP(TbProventos[[#This Row],[Ativo]],TbAtivos!$C$3:$E$500,2,FALSE) -> FII
B12: 14 | C12: KNRI11 | D12: 100 | E12: 61.75 | F12: 0 | G12: 61.75 | H12: 43482 | I12: =CONCATENATE(YEAR(TbProventos[[#This Row],[Data]]),"/",IF(MONTH(TbProventos[[#This Row],[Data]])<10,"0",""),MONTH(TbProventos[[#This Row],[Data]])) -> 2019/01 | J12: =VLOOKUP(TbProventos[[#This Row],[Ativo]],TbAtivos!$C$3:$E$500,2,FALSE) -> FII
B13: 13 | C13: ITSA4 | D13: 100 | E13: 65.43 | F13: 0 | G13: 65.43 | H13: 43511 | I13: =CONCATENATE(YEAR(TbProventos[[#This Row],[Data]]),"/",IF(MONTH(TbProventos[[#This Row],[Data]])<10,"0",""),MONTH(TbProventos[[#This Row],[Data]])) -> 2019/02 | J13: =VLOOKUP(TbProventos[[#This Row],[Ativo]],TbAtivos!$C$3:$E$500,2,FALSE) -> EMPRESA
B14: 50 | C14: HGBS12 | D14: 100 | E14: 0 | F14: 0 | G14: 0 | H14: 43511 | I14: =CONCATENATE(YEAR(TbProventos[[#This Row],[Data]]),"/",IF(MONTH(TbProventos[[#This Row],[Data]])<10,"0",""),MONTH(TbProventos[[#This Row],[Data]])) -> 2019/02 | J14: =VLOOKUP(TbProventos[[#This Row],[Ativo]],TbAtivos!$C$3:$E$500,2,FALSE) -> #N/A
... B73: 14 | C73: KNRI11 | D73: 100 | E73: 153.18 | F73: 0 | G73: 153.18 | H73: 43847 | I73: =CONCATENATE(YEAR(TbProventos[[#This Row],[Data]]),"/",IF(MONTH(TbProventos[[#This Row],[Data]])<10,"0",""),MONTH(TbProventos[[#This Row],[Data]])) -> 2020/01 | J73: =VLOOKUP(TbProventos[[#This Row],[Ativo]],TbAtivos!$C$3:$E$500,2,FALSE) -> FII

Sheet TbAtivos
A1: Planilha sem tÃ­tulo : PÃ¡gina1
C2: ATIVO | D2: TIPO | E2: COTACAO
A3: 1 | C3: CSNA3 | D3: EMPRESA | E3: 7.88
A4: 2 | C4: FLRY3 | D4: EMPRESA | E4: 20.15
A5: 3 | C5: ITSA4 | D5: EMPRESA | E5: 8.14
A6: 4 | C6: PETR4 | D6: EMPRESA | E6: 17.15
A7: 5 | C7: HGBS11 | D7: FII | E7: 194.98
A8: 6 | C8: HGLG11 | D8: FII | E8: 174.47
A9: 7 | C9: HGRE11 | D9: FII | E9: 141.94
A10: 8 | C10: KNRI11 | D10: FII | E10: 161.91
A11: 9 | C11: TAEE4 | D11: EMPRESA | E11: 9.05
A12: 10
A13: Published by Google Sheets–Denunciar abuso–5Atualizado automaticamente a cada minutos
